README.md
setup.cfg
setup.py
ttabooster/TTABoost.py
ttabooster/__init__.py
ttabooster/cifar_utils.py
ttabooster/datasets.py
ttabooster/usage_example.py
ttabooster.egg-info/PKG-INFO
ttabooster.egg-info/SOURCES.txt
ttabooster.egg-info/dependency_links.txt
ttabooster.egg-info/not-zip-safe
ttabooster.egg-info/requires.txt
ttabooster.egg-info/top_level.txt