Metadata-Version: 2.1
Name: ttabooster
Version: 0.13
Summary: Boost pretrained models with test time augmentation selection
Home-page: https://github.com/OmriKaduri/ttabooster
Author: Seffi Cohen, Omri Kaduri
Author-email: Kaduriomri@gmail.com
License: MIT
Download-URL: https://github.com/OmriKaduri/ttabooster/releases/tag/0.13
Platform: UNKNOWN
